CONTRIBUTING.md
MANIFEST.in
README.rst
setup.py
docs/HISTORY.txt
docs/LICENSE.GPL
docs/LICENSE.txt
eea/__init__.py
eea.coremetadata.egg-info/PKG-INFO
eea.coremetadata.egg-info/SOURCES.txt
eea.coremetadata.egg-info/dependency_links.txt
eea.coremetadata.egg-info/entry_points.txt
eea.coremetadata.egg-info/namespace_packages.txt
eea.coremetadata.egg-info/not-zip-safe
eea.coremetadata.egg-info/requires.txt
eea.coremetadata.egg-info/top_level.txt
eea/coremetadata/README.txt
eea/coremetadata/__init__.py
eea/coremetadata/configure.zcml
eea/coremetadata/index_modifiers.py
eea/coremetadata/indexer.py
eea/coremetadata/interfaces.py
eea/coremetadata/metadata.py
eea/coremetadata/profiles.zcml
eea/coremetadata/setuphandlers.py
eea/coremetadata/version.txt
eea/coremetadata/vocabulary.py
eea/coremetadata/behaviors/__init__.py
eea/coremetadata/behaviors/configure.zcml
eea/coremetadata/behaviors/metadata.py
eea/coremetadata/behaviors/vocabulary.py
eea/coremetadata/browser/__init__.py
eea/coremetadata/browser/configure.zcml
eea/coremetadata/locales/__init__.py
eea/coremetadata/locales/eea.pot
eea/coremetadata/locales/plone-manual.pot
eea/coremetadata/locales/update.sh
eea/coremetadata/locales/bg/LC_MESSAGES/eea.mo
eea/coremetadata/locales/bg/LC_MESSAGES/eea.po
eea/coremetadata/locales/bg/LC_MESSAGES/plone.mo
eea/coremetadata/locales/bg/LC_MESSAGES/plone.po
eea/coremetadata/locales/cs/LC_MESSAGES/eea.mo
eea/coremetadata/locales/cs/LC_MESSAGES/eea.po
eea/coremetadata/locales/cs/LC_MESSAGES/plone.mo
eea/coremetadata/locales/cs/LC_MESSAGES/plone.po
eea/coremetadata/locales/da/LC_MESSAGES/eea.mo
eea/coremetadata/locales/da/LC_MESSAGES/eea.po
eea/coremetadata/locales/da/LC_MESSAGES/plone.mo
eea/coremetadata/locales/da/LC_MESSAGES/plone.po
eea/coremetadata/locales/de/LC_MESSAGES/eea.mo
eea/coremetadata/locales/de/LC_MESSAGES/eea.po
eea/coremetadata/locales/de/LC_MESSAGES/plone.mo
eea/coremetadata/locales/de/LC_MESSAGES/plone.po
eea/coremetadata/locales/el/LC_MESSAGES/eea.mo
eea/coremetadata/locales/el/LC_MESSAGES/eea.po
eea/coremetadata/locales/el/LC_MESSAGES/plone.mo
eea/coremetadata/locales/el/LC_MESSAGES/plone.po
eea/coremetadata/locales/en/LC_MESSAGES/eea.mo
eea/coremetadata/locales/en/LC_MESSAGES/eea.po
eea/coremetadata/locales/en/LC_MESSAGES/plone.mo
eea/coremetadata/locales/en/LC_MESSAGES/plone.po
